agmodeling/.gitignore
agmodeling/__init__.py
agmodeling/scoring/.gitignore
agmodeling/scoring/__init__.py
agmodeling/scoring/set_method.py
agmodeling-0.10.dist-info/LICENSE
agmodeling-0.10.dist-info/METADATA
agmodeling-0.10.dist-info/WHEEL
agmodeling-0.10.dist-info/top_level.txt
agmodeling-0.10.dist-info/RECORD
