Metadata-Version: 2.1
Name: agmodeling
Version: 0.10
Summary: Statistical modeling tools, to unify model creation and scoring based on python
Home-page: https://github.com/agriscope/agmodeling/
Author: Agriscope
Author-email: team@agriscope.fr
License: UNKNOWN
Platform: UNKNOWN
Classifier: Programming Language :: Python
Classifier: Development Status :: 1 - Planning
Classifier: License :: OSI Approved :: GNU Lesser General Public License v3 (LGPLv3)
Classifier: Natural Language :: French
Classifier: Operating System :: OS Independent
Classifier: Programming Language :: Python :: 2.7
Classifier: Topic :: Database :: Database Engines/Servers
License-File: LICENSE
